<?xml version="1.0"?>
<GhussakTweaks>
  <append xpath="/blocks">
  </append>
  <append xpath="/blocks/block[@name='cntStoreElectronicsPalletTvFallen']">
    <drop event="Harvest" name="electronicsParts" count="2" tag="allHarvest"/>
  </append>
  <append xpath="/blocks/block[@name='cntStoreElectronicsPalletTvStanding']">
    <drop event="Harvest" name="electronicsParts" count="8" tag="allHarvest"/>
  </append>
  <append xpath="/blocks/block[   @name='cntATMInsecure' or   @name='cntHardenedChestInsecure' or   @name='cntHardenedChestInsecureT5'  ]">
    <drop event="Harvest" name="electronicsParts" count="1,2" tag="salvageHarvest"/>
    <drop event="Harvest" name="NightVisionBattery" count="5,10" tag="salvageHarvest"/>
  </append>
</GhussakTweaks>
